LICENSE
MANIFEST.in
README.md
requirements.txt
setup.py
aioEasyPillow/__init__.py
aioEasyPillow/canvas.py
aioEasyPillow/editor.py
aioEasyPillow/font.py
aioEasyPillow/text.py
aioEasyPillow/utils.py
aioEasyPillow.egg-info/PKG-INFO
aioEasyPillow.egg-info/SOURCES.txt
aioEasyPillow.egg-info/dependency_links.txt
aioEasyPillow.egg-info/requires.txt
aioEasyPillow.egg-info/top_level.txt
aioEasyPillow/fonts/caveat/caveat.ttf
aioEasyPillow/fonts/montserrat/montserrat_bold.ttf
aioEasyPillow/fonts/montserrat/montserrat_italic.ttf
aioEasyPillow/fonts/montserrat/montserrat_light.ttf
aioEasyPillow/fonts/montserrat/montserrat_regular.ttf
aioEasyPillow/fonts/poppins/poppins_bold.ttf
aioEasyPillow/fonts/poppins/poppins_italic.ttf
aioEasyPillow/fonts/poppins/poppins_light.ttf
aioEasyPillow/fonts/poppins/poppins_regular.ttf